mycalc/calculator.py
dongkyu-0.0.1.dist-info/METADATA
dongkyu-0.0.1.dist-info/WHEEL
dongkyu-0.0.1.dist-info/top_level.txt
dongkyu-0.0.1.dist-info/RECORD
