Metadata-Version: 2.1
Name: dongkyu
Version: 0.0.1
Summary: nice calculator
Home-page: https://github.com/dongkyukim/calc0001
Download-URL: https://github.com/dongkyukim/calc001
Classifier: Programming Language :: Python :: 3
